Metadata-Version: 1.2
Name: fever-allennlp
Version: 1.0.8
Summary: Fact Extraction and VERification experiments built on AllenNLP
Home-page: https://jamesthorne.co.uk
Author: James Thorne
Author-email: james@jamesthorne.co.uk
License: See http://www.python.org/3.6/license.html
Platform: UNKNOWN
Requires-Python: >=3.6
